{
    "telnet": {
        "GNS3_server_url": "www.telnet.com",
        "port": 5000,
        "projet_name": "GNS3"
    },

    "domain": [
        {
        "AS": "AS100",
        "protocol": "RIP",
        "router": ["R11", "R12", "R13","R14", "R15", "R16", "R17"]
        },
        {
        "AS": "AS200",
        "protocol": "OSPF",
        "router": ["R21", "R22", "R23","R24", "R25", "R26", "R27"]
        }
    ],

    "reseau": [
        [["R11", "GigabitEthernet1/0"], ["R12", "GigabitEthernet1/0"]],
        [["R11", "GigabitEthernet2/0"], ["R13", "GigabitEthernet2/0"]],
        [["R12", "GigabitEthernet3/0"], ["R13", "GigabitEthernet3/0"]],
        [["R12", "GigabitEthernet2/0"], ["R14", "GigabitEthernet2/0"]],
        [["R13", "GigabitEthernet1/0"], ["R15", "GigabitEthernet1/0"]]
    ]
}